oscar.so
oscar-2.2.0.dist-info/RECORD
oscar-2.2.0.dist-info/METADATA
oscar-2.2.0.dist-info/top_level.txt
oscar-2.2.0.dist-info/WHEEL
oscar-2.2.0.dist-info/LICENSE
oscar.libs/libbz2-13e8c345.so.1.0.4
oscar.libs/libz-eb09ad1d.so.1.2.3
