Metadata-Version: 2.1
Name: oscar
Version: 2.2.0
Summary: A Python interface to OSCAR data
Home-page: https://github.com/ssc-oscar/oscar.py
Author: marat@cmu.edu
Author-email: marat@cmu.edu
License: GPL v3
Platform: UNKNOWN
Classifier: Development Status :: 4 - Beta
Classifier: Intended Audience :: Science/Research
Classifier: Programming Language :: Cython
Classifier: License :: OSI Approved :: GNU General Public License v3 (GPLv3)
Classifier: Operating System :: POSIX :: Linux
Classifier: Topic :: Scientific/Engineering
Requires-Python: >2.6, !=3.0.*, !=3.1.*, !=3.2.*, !=3.3.*, !=3.4.*,  <4
Requires-Dist: python-lzf
Requires-Dist: typing
